asgi_log_to_sqlite.py
asgi_log_to_sqlite-0.1.1.dist-info/LICENSE
asgi_log_to_sqlite-0.1.1.dist-info/METADATA
asgi_log_to_sqlite-0.1.1.dist-info/WHEEL
asgi_log_to_sqlite-0.1.1.dist-info/top_level.txt
asgi_log_to_sqlite-0.1.1.dist-info/RECORD
