Metadata-Version: 2.1
Name: asgi-log-to-sqlite
Version: 0.1.1
Summary: ASGI middleware for logging traffic to a SQLite database
Home-page: https://github.com/simonw/asgi-log-to-sqlite
Author: Simon Willison
License: Apache License, Version 2.0
Platform: UNKNOWN
Requires-Dist: sqlite-utils (~=2.3.1)
Provides-Extra: test
Requires-Dist: pytest ; extra == 'test'
Requires-Dist: pytest-asyncio ; extra == 'test'
Requires-Dist: asgiref (==3.1.2) ; extra == 'test'
